{
  "timestamp_utc": "20260608_124919",
  "strategy": "BtcBreakoutBossStrategy",
  "mode": "CBT_Breakout_Boss_2018",
  "pair": "BTC/USDT",
  "timerange": "20180101-20190101",
  "wallet": 10000.0,
  "notes": "COMPRE_Breakout Boss",
  "strategy_class": "BtcBreakoutBossStrategy",
  "starting_balance": 10000.0,
  "final_balance": 8808.21171272,
  "total_pnl": -1191.78828728,
  "roi_pct": -11.918,
  "n_trades": 1,
  "wins": 0,
  "losses": 1,
  "win_rate_pct": 0.0,
  "max_dd_pct": 11.918,
  "max_dd_abs": 1191.78828728,
  "sharpe": -100.0,
  "sortino": -100.0,
  "calmar": -5.234,
  "profit_factor": 0.0,
  "expectancy": -1191.7883,
  "best_trade_pct": 0.0,
  "worst_trade_pct": 0.0,
  "avg_trade_duration": "",
  "backtest_start": "2018-01-01 00:00:00",
  "backtest_end": "2019-01-01 00:00:00"
}