{
  "timestamp_utc": "20260606_110154",
  "strategy": "BtcMacroV2Strategy",
  "mode": "SWEEP",
  "pair": "BTC/USDT",
  "timerange": "20180101-20260601",
  "wallet": 10000.0,
  "notes": "sweep {'MV_W_MACRO': 0.05, 'MV_W_VIX': 0.1, 'MV_W_SPY': 0.1, 'MV_W_QQQ': 0.05, 'MV_W_DXY': 0.0, 'MV_W_RATES': 0.0, 'MV_EXIT_THR': -0.5, 'MV_MODE': 'tilt'}",
  "strategy_class": "BtcMacroV2Strategy",
  "starting_balance": 10000.0,
  "final_balance": 92181.63383524002,
  "total_pnl": 82181.63383524,
  "roi_pct": 821.816,
  "n_trades": 30,
  "wins": 22,
  "losses": 8,
  "win_rate_pct": 73.33,
  "max_dd_pct": 18.185,
  "max_dd_abs": 15400.964967949993,
  "sharpe": 0.066,
  "sortino": 0.124,
  "calmar": 28.875,
  "profit_factor": 3.023,
  "expectancy": 2739.3878,
  "best_trade_pct": 0.0,
  "worst_trade_pct": 0.0,
  "avg_trade_duration": "",
  "backtest_start": "2018-03-25 00:00:00",
  "backtest_end": "2026-06-01 00:00:00"
}