{
  "timestamp_utc": "20260607_144238",
  "strategy": "BtcAnalogV2Strategy",
  "mode": "REAL_2024",
  "pair": "BTC/USDT",
  "timerange": "20240101-20250101",
  "wallet": 10000.0,
  "notes": "realistic slippage",
  "strategy_class": "BtcAnalogV2Strategy",
  "starting_balance": 10000.0,
  "final_balance": 12779.08163044,
  "total_pnl": 2779.0816304399996,
  "roi_pct": 27.791,
  "n_trades": 4,
  "wins": 3,
  "losses": 1,
  "win_rate_pct": 75.0,
  "max_dd_pct": 13.937,
  "max_dd_abs": 2069.38206574,
  "sharpe": 0.072,
  "sortino": -100.0,
  "calmar": 10.409,
  "profit_factor": 2.343,
  "expectancy": 694.7704,
  "best_trade_pct": 0.0,
  "worst_trade_pct": 0.0,
  "avg_trade_duration": "",
  "backtest_start": "2024-01-01 00:00:00",
  "backtest_end": "2025-01-01 00:00:00"
}