{
  "timestamp_utc": "20260604_111748",
  "strategy": "CalendarFuturesStrategy",
  "mode": "ETHFUTV2_2024",
  "pair": "BTC/USDT",
  "timerange": "20240101-20250101",
  "wallet": 10000.0,
  "notes": "ETH Calendar Futures v2 with rebalance",
  "strategy_class": "CalendarFuturesStrategy",
  "starting_balance": 10000.0,
  "final_balance": 10048.50418389,
  "total_pnl": 48.50418388999995,
  "roi_pct": 0.485,
  "n_trades": 3,
  "wins": 1,
  "losses": 2,
  "win_rate_pct": 33.33,
  "max_dd_pct": 6.5,
  "max_dd_abs": 698.6019551400001,
  "sharpe": 0.005,
  "sortino": 0.009,
  "calmar": 0.389,
  "profit_factor": 1.069,
  "expectancy": 16.1681,
  "best_trade_pct": 0.0,
  "worst_trade_pct": 0.0,
  "avg_trade_duration": "",
  "backtest_start": "2024-01-01 00:00:00",
  "backtest_end": "2025-01-01 00:00:00"
}