{
  "timestamp_utc": "20260604_140948",
  "strategy": "SolVolShieldStrategy",
  "mode": "DOT_VOL_2024",
  "pair": "BTC/USDT",
  "timerange": "20240101-20250101",
  "wallet": 10000.0,
  "notes": "DOT VolShield",
  "strategy_class": "SolVolShieldStrategy",
  "starting_balance": 10000.0,
  "final_balance": 8862.98060146,
  "total_pnl": -1137.01939854,
  "roi_pct": -11.37,
  "n_trades": 2,
  "wins": 0,
  "losses": 2,
  "win_rate_pct": 0.0,
  "max_dd_pct": 11.37,
  "max_dd_abs": 1137.01939854,
  "sharpe": -0.146,
  "sortino": -0.146,
  "calmar": -5.22,
  "profit_factor": 0.0,
  "expectancy": -568.5097,
  "best_trade_pct": 0.0,
  "worst_trade_pct": 0.0,
  "avg_trade_duration": "",
  "backtest_start": "2024-01-01 00:00:00",
  "backtest_end": "2025-01-01 00:00:00"
}