{
  "timestamp_utc": "20260608_134852",
  "strategy": "BtcRotationStrategy",
  "mode": "CBT_Rotation_Multi_2026",
  "pair": "BTC/USDT",
  "timerange": "20260101-20260601",
  "wallet": 10000.0,
  "notes": "COMPRE_Rotation Multi",
  "strategy_class": "BtcRotationStrategy",
  "starting_balance": 10000.0,
  "final_balance": 9453.33122085,
  "total_pnl": -546.66877915,
  "roi_pct": -5.467,
  "n_trades": 4,
  "wins": 1,
  "losses": 3,
  "win_rate_pct": 25.0,
  "max_dd_pct": 5.467,
  "max_dd_abs": 546.66877915,
  "sharpe": -0.472,
  "sortino": -0.518,
  "calmar": -12.652,
  "profit_factor": 0.033,
  "expectancy": -136.6672,
  "best_trade_pct": 0.0,
  "worst_trade_pct": 0.0,
  "avg_trade_duration": "",
  "backtest_start": "2026-01-01 00:00:00",
  "backtest_end": "2026-06-01 00:00:00"
}