{
  "timestamp_utc": "20260605_001234",
  "strategy": "BtcTripleRegimeStrategy",
  "mode": "MY_BNB_Triple_2019",
  "pair": "BTC/USDT",
  "timerange": "20190101-20200101",
  "wallet": 10000.0,
  "notes": "multi-year BNB_Triple 2019",
  "strategy_class": "BtcTripleRegimeStrategy",
  "starting_balance": 10000.0,
  "final_balance": 12257.45190554,
  "total_pnl": 2257.4519055399996,
  "roi_pct": 22.575,
  "n_trades": 2,
  "wins": 2,
  "losses": 0,
  "win_rate_pct": 100.0,
  "max_dd_pct": 0.0,
  "max_dd_abs": 0.0,
  "sharpe": 3.576,
  "sortino": -100.0,
  "calmar": -100.0,
  "profit_factor": 0.0,
  "expectancy": 1128.726,
  "best_trade_pct": 0.0,
  "worst_trade_pct": 0.0,
  "avg_trade_duration": "",
  "backtest_start": "2019-01-01 00:00:00",
  "backtest_end": "2020-01-01 00:00:00"
}